{
  "project_info": {
    "project_number": "548393081270",
    "project_id": "studymatch-58b0c",
    "storage_bucket": "studymatch-58b0c.appspot.com"
  },
  "client": [
    {
      "client_info": {
        "mobilesdk_app_id": "1:548393081270:android:6c215e7267e7b0c6fc8917",
        "android_client_info": {
          "package_name": "com.example.proyecto1ppm"
        }
      },
      "oauth_client": [],
      "api_key": [
        {
          "current_key": "AIzaSyAezlW_ZVRNCBZa--Odw2Dyv5JS_YKpBbk"
        }
      ],
      "services": {
        "appinvite_service": {
          "other_platform_oauth_client": []
        }
      }
    }
  ],
  "configuration_version": "1"
}